{
  "GroupID": "engineer.echo",
  "ArtifactID": "happymaven",
  "Versions": [
    {
      "Version": "0.0.1",
      "SHA1": "kGuai9BY8PRL+OvCNRiu9SsFBGw="
    },
    {
      "Version": "0.0.2",
      "SHA1": "ErKtNplls9OKOxlDl60ftWebeCo="
    },
    {
      "Version": "0.0.3",
      "SHA1": "iY0VIu4VZz+ojn2v8gcHWCNjYNE="
    },
    {
      "Version": "0.0.4",
      "SHA1": "WA0C9AvKT+DOjev1UyXRHF7wXtY="
    },
    {
      "Version": "0.0.6",
      "SHA1": "bQf2eTrJfp51QbYGdPJWgsDnVQA="
    },
    {
      "Version": "0.0.7",
      "SHA1": "vkRrI06NPEc3yuk6pW1v4dVZ10o="
    },
    {
      "Version": "0.0.9",
      "SHA1": "jiuS7pWSTobrcTI/vf+fjoChyus="
    }
  ],
  "ArchiveType": "jar"
}