{
  "GroupID": "cc.neckbeard",
  "ArtifactID": "TinyEventBus",
  "Versions": [
    {
      "Version": "2.0.0",
      "SHA1": "+6yCCheDZbpu6Xw18Jj2232WMrw="
    },
    {
      "Version": "2.0.1",
      "SHA1": "8VwMUqQIa4lbwJg67Kf0q0er9z4="
    },
    {
      "Version": "2.0.5",
      "SHA1": "dB1Ucu8Am3mGClPCLYdD4mxf1zo="
    },
    {
      "Version": "2.0.6",
      "SHA1": "bCtAh6ZuSD2mzGBTdu9x/He4Hbg="
    },
    {
      "Version": "2.0.7",
      "SHA1": "nwDbUlUB0Rd3cA1v7MpboLqVreI="
    },
    {
      "Version": "3.0.0",
      "SHA1": "IImS6cjeqOBREsiBZPmZpmhIey0="
    },
    {
      "Version": "3.0.1",
      "SHA1": "gQyIzSq1q4XMtnyJ3441NBv3rHc="
    },
    {
      "Version": "3.0.2",
      "SHA1": "HOXOGakW6QEieFARCCl9vjKpMQM="
    },
    {
      "Version": "3.0.3",
      "SHA1": "wm8NxyxO57dkKtcLuHOh5MGptxM="
    }
  ],
  "ArchiveType": "jar"
}