{
  "GroupID": "berkano",
  "ArtifactID": "berkano-taglib-unit",
  "Versions": [
    {
      "Version": "20050615.232615",
      "SHA1": "zb/MYnNJz34gV7Pggi00hKFkwkY="
    },
    {
      "Version": "20050615.234701",
      "SHA1": "zb/MYnNJz34gV7Pggi00hKFkwkY="
    },
    {
      "Version": "20050616.000547",
      "SHA1": "zb/MYnNJz34gV7Pggi00hKFkwkY="
    },
    {
      "Version": "20050616.001606",
      "SHA1": "U98gE+Lpc1I1Y4oJIouJ5jdmxuk="
    },
    {
      "Version": "20050616.003439",
      "SHA1": "U98gE+Lpc1I1Y4oJIouJ5jdmxuk="
    },
    {
      "Version": "20050616.015440",
      "SHA1": "ukyL0u+vFWbWBME83FPNKam7s2c="
    },
    {
      "Version": "20050809",
      "SHA1": "RzohwGSVzjg8aYPa/xN1r0E7joY="
    },
    {
      "Version": "dev-20050722",
      "SHA1": "LxoXJRKSiPZmOKbtesvR4K7o8IA="
    },
    {
      "Version": "dev-20050723",
      "SHA1": "L0+ti/aCZD41vD7irILyDOkXbXY="
    },
    {
      "Version": "20050725.114152",
      "SHA1": "mwadbOdJSDg0mysIZFoqDUzX6/s="
    },
    {
      "Version": "20050901",
      "SHA1": "iURYzoKyyKprNIVKpf+KRzoG8/I="
    },
    {
      "Version": "20050901-2",
      "SHA1": "uQJmlYApv6Oe9nTMFUTfH7RW2eU="
    },
    {
      "Version": "20050901.201035",
      "SHA1": "vnMZ5UZR13/JfSCtcLbL9kWtGs8="
    },
    {
      "Version": "20050805.043354",
      "SHA1": "HpMPiaCDjdB/dsUoC3zsu0I1BtQ="
    }
  ],
  "ArchiveType": "jar"
}