{
  "GroupID": "fr.hhdev",
  "ArtifactID": "ocelot-core",
  "Versions": [
    {
      "Version": "1.0.1",
      "SHA1": "hnOk82R/lSI5Et33JkCsDQkFNEU="
    },
    {
      "Version": "1.0.2",
      "SHA1": "UlsraZ/GtRTIEfDYgvfbrVzmQws="
    },
    {
      "Version": "1.2.0",
      "SHA1": "lsG84oeZsGyDzF+tg3dSc4BmwSs="
    },
    {
      "Version": "1.3.0",
      "SHA1": "neZ+NhZgWsQLGHOVXDpMdN2+/mk="
    },
    {
      "Version": "1.3.1",
      "SHA1": "eI+UkGwjcFYfdChEkXbgaF3YKps="
    },
    {
      "Version": "2.0.0",
      "SHA1": "ODRxJpd8Mt3sevwNm7UAYpp39YI="
    },
    {
      "Version": "2.0.1",
      "SHA1": "6XONPzYbkhvSG239BiJbuAAkHhI="
    },
    {
      "Version": "2.0.2",
      "SHA1": "K19xLlRljTAOCTM51pdyRD5yuh0="
    }
  ],
  "ArchiveType": "jar"
}