{
  "GroupID": "africa.absa",
  "ArtifactID": "inception-application",
  "Versions": [
    {
      "Version": "1.0.0",
      "SHA1": "OxJ43Mbyw8XwAey4e/lJOJ+ZK6c="
    },
    {
      "Version": "1.0.1",
      "SHA1": "sOnl+2heE0AQx0vCS2AIce+QvhM="
    },
    {
      "Version": "1.1.0",
      "SHA1": "6rxdgRy3QKHySp5W49iC4zYhmfw="
    },
    {
      "Version": "1.1.1",
      "SHA1": "wd/QxTsNVJmgCIe3KxCOiQrYv3E="
    },
    {
      "Version": "1.2.0",
      "SHA1": "lJzDsFDvPK0i8ekhQ6ErK2A96zA="
    }
  ],
  "ArchiveType": "jar"
}