{
  "GroupID": "store.idragon.tool",
  "ArtifactID": "word",
  "Versions": [
    {
      "Version": "0.0.1-RELEASE",
      "SHA1": "fmfpcRh5MYYyUIGwWmdc56iKL38="
    },
    {
      "Version": "0.0.2-RELEASE",
      "SHA1": "ii8mTpPdUoJs/nP08HlMxChqnt0="
    },
    {
      "Version": "0.0.3-RELEASE",
      "SHA1": "iiJ/OcQ/oXY6uqaiN4bYbUU8+EM="
    },
    {
      "Version": "0.0.4-RELEASE",
      "SHA1": "msxYpojKF8ThyYw6U9hnWAru2bI="
    },
    {
      "Version": "0.0.5-RELEASE",
      "SHA1": "6aniNnNyEZgWq/5s0AZ9CIg670Q="
    },
    {
      "Version": "0.0.6-RELEASE",
      "SHA1": "CF9nE7T7ribM9ZxPDZYcGVUPVMk="
    }
  ],
  "ArchiveType": "jar"
}