{
  "GroupID": "vip.mate",
  "ArtifactID": "mate-starter-dubbo",
  "Versions": [
    {
      "Version": "1.6.8",
      "SHA1": "p56NxgXMRlaDYvPF7X/puznodkQ="
    },
    {
      "Version": "2.0.8",
      "SHA1": "8KOt4wVDphEuf9hYmKnHUPG1yGc="
    },
    {
      "Version": "2.1.8",
      "SHA1": "DKsCKiz5W5R9MjFJoI37ZabTdj0="
    },
    {
      "Version": "2.2.8",
      "SHA1": "D/qQJU8aMLcwltPE7JCWq22pbZE="
    },
    {
      "Version": "2.3.8",
      "SHA1": "BYOwYBXEBJ+Pcod56s8YiX3gEOI="
    },
    {
      "Version": "2.5.8",
      "SHA1": "AQGsc7R5hju86zVLJxwcPreyjnU="
    },
    {
      "Version": "3.0.8",
      "SHA1": "MfZ/W1iHbweAhYimT24dBuV7VJ0="
    },
    {
      "Version": "3.1.8",
      "SHA1": "+trWfzAwsBlLJ81Vk2YUXL7Au4g="
    },
    {
      "Version": "3.2.8",
      "SHA1": "wRkAPondKGFQkpFjIWK2ItQUwDY="
    },
    {
      "Version": "3.3.8",
      "SHA1": "/6Lt2tv+HUaCl+4o/GGS1dewofU="
    },
    {
      "Version": "3.5.8",
      "SHA1": "9gsET66AkbmcQM1xX9/iwm7gwc8="
    },
    {
      "Version": "3.6.8",
      "SHA1": "JqpWpwHsiVUuhyY8B259LwE135s="
    },
    {
      "Version": "3.7.8",
      "SHA1": "UBYC9uvk8yjx8PBwlejIPm+W6zs="
    },
    {
      "Version": "3.8.8",
      "SHA1": "zz6qLpvpG9B62vkTXFePQGeAGfA="
    },
    {
      "Version": "4.0.8",
      "SHA1": "QQGfvsXzOG7KMCymZX6gmoFMGJw="
    },
    {
      "Version": "4.0.9",
      "SHA1": "hNgT9ehEKbP9vx8t6stODRmSFS4="
    },
    {
      "Version": "4.0.10",
      "SHA1": "LLVJgIOeM76ib2O7H5ExXrEC7SU="
    },
    {
      "Version": "4.0.11",
      "SHA1": "KhVPcQPDFIvx3HCZjCj5yEW+vks="
    },
    {
      "Version": "4.1.8",
      "SHA1": "OOUwmOVPIH0MUIKnCmDlro7wzSs="
    },
    {
      "Version": "4.2.8",
      "SHA1": "Ioo1IYLDk9zoqXfb56MxiSNWcW8="
    },
    {
      "Version": "4.3.8",
      "SHA1": "Yi9x3aZRZiQieTQXeg93jVRK9V0="
    },
    {
      "Version": "4.4.8",
      "SHA1": "hxrGnn73JJXLIEsjkuiXACRp0fU="
    },
    {
      "Version": "4.5.8",
      "SHA1": "oKWJhrt/3fUoEbdXN0dIyqJgHTw="
    },
    {
      "Version": "4.6.8",
      "SHA1": "0U49ormOuoJaE3t9sckivt8sED4="
    }
  ],
  "ArchiveType": "jar"
}