{
  "GroupID": "travel.wink",
  "ArtifactID": "analytics",
  "Versions": [
    {
      "Version": "21.16.3",
      "SHA1": "0/pqJfQ6paJtzggj/t7hny6mDdU="
    },
    {
      "Version": "22.0.1",
      "SHA1": "uRYs8njDikI5CW6c1XF2ROQpBAU="
    },
    {
      "Version": "23.1.1",
      "SHA1": "T0M+6Nd/7SLMvw8fnmnt+y2zVIw="
    },
    {
      "Version": "24.0.0",
      "SHA1": "ORmh3rdHWEy/MLXf66OKTOKZacY="
    },
    {
      "Version": "24.3.2",
      "SHA1": "IuJeHS8hiX9vMeCXX3jDhXD4pb8="
    },
    {
      "Version": "24.7.0",
      "SHA1": "0KxacFuo7JsluME/m40iYZLk0Ag="
    },
    {
      "Version": "25.0.3",
      "SHA1": "Gse7l0G5zSASi+atcR3AzW0rAfo="
    },
    {
      "Version": "25.1.0",
      "SHA1": "m+I46JeTfw/5zrbi3AMkLe3kcTE="
    },
    {
      "Version": "25.2.3",
      "SHA1": "/6yQPQ8Vei/kHSey+lewCzDhX28="
    },
    {
      "Version": "25.2.7",
      "SHA1": "EwPZ8tQ6eIrEMTMbmoulbu9Cc6A="
    },
    {
      "Version": "25.3.0",
      "SHA1": "m7i+q/YEaNNgTZwdEPhU9kJWcFk="
    },
    {
      "Version": "25.4.2",
      "SHA1": "6B2b7xhkOUprLrCYKFkznXbtYpY="
    },
    {
      "Version": "25.6.4",
      "SHA1": "jV2mSinZth2mwWv17VVad+wjoSk="
    },
    {
      "Version": "25.6.8",
      "SHA1": "vqD5h9qslRELZ8UG9Z9KCbkAMvM="
    },
    {
      "Version": "26.0.3",
      "SHA1": "jSkESIg6MadSWRwUhjGQP3GYVhA="
    },
    {
      "Version": "26.1.1",
      "SHA1": "b9EdEEcfYj9UM3ISv2kelVJ7bfc="
    },
    {
      "Version": "27.1.1",
      "SHA1": "ONV8iZpgWzI9Orkx8TAHFpkeEw8="
    },
    {
      "Version": "29.0.0",
      "SHA1": "hVQev4k3jq820ZWp2pnLmWUA2YM="
    },
    {
      "Version": "29.3.0",
      "SHA1": "3o9JBtsPgHS7dnFadmdmrV5H3Uk="
    },
    {
      "Version": "29.7.0",
      "SHA1": "JZe4raRT7J1ZBLiBPePjGONJS2s="
    },
    {
      "Version": "29.8.0",
      "SHA1": "o6pFCtcvi5GWNtnMpgmR8Oa5YEE="
    },
    {
      "Version": "29.8.3",
      "SHA1": "IsKTVbRlOB+mqJAjOGKI0Uze6f8="
    },
    {
      "Version": "29.8.8",
      "SHA1": "LobImyMEqKl5bNFeDVSVgLfOn4g="
    },
    {
      "Version": "29.10.0",
      "SHA1": "6GXSsDhng3NyXYF/8NJkxziwWfo="
    }
  ],
  "ArchiveType": "jar"
}