{
  "GroupID": "plus.jdk",
  "ArtifactID": "spring-boot-starter-monitor",
  "Versions": [
    {
      "Version": "1.0.0",
      "SHA1": "Qq6BSxio63NRLfBHtLxeXqviYas="
    },
    {
      "Version": "1.0.1",
      "SHA1": "3EUSeMkUWJvC/m/nwH9eNCTvrTw="
    },
    {
      "Version": "1.0.3",
      "SHA1": "oP9Vc4bytW0IJ0OVdE1vroYORYY="
    },
    {
      "Version": "1.0.4",
      "SHA1": "wt9JQxuEyWV9mQFuDrGUt2lWSdY="
    },
    {
      "Version": "1.0.5",
      "SHA1": "BUtjiKz7V+pawcCfVoqNzh42P3A="
    }
  ],
  "ArchiveType": "jar"
}