{
  "GroupID": "be.doeraene",
  "ArtifactID": "urldsl_2.12",
  "Versions": [
    {
      "Version": "0.1.3",
      "SHA1": "g5Dd7Mq0/kGtAKxgNR0clP8j8kQ="
    },
    {
      "Version": "0.1.4",
      "SHA1": "wm6PX9rTh/J0xS7JbZFAelZFDxU="
    },
    {
      "Version": "0.2.0",
      "SHA1": "SAyIx5QClNXEkQsoGHPyUZ1yFOk="
    },
    {
      "Version": "0.3.2",
      "SHA1": "XzrxI8TkgfnHIb1nyr9tf405iPY="
    },
    {
      "Version": "0.4.0",
      "SHA1": "QwflDmKB8KfmunDc/KfrGF4F/Zw="
    }
  ],
  "ArchiveType": "jar"
}