{
  "GroupID": "nekohtml",
  "ArtifactID": "nekohtmlXni",
  "Versions": [
    {
      "Version": "0.7.1",
      "SHA1": "zgxHOmKPUYdJrob05EuFumAY2b8="
    },
    {
      "Version": "0.7.6",
      "SHA1": "iLiM0kVzWOjv9GYnHEP+IBKyHzI="
    },
    {
      "Version": "0.7.7",
      "SHA1": "JL9hgxZzANTPHRi1XS6ACWahuL8="
    },
    {
      "Version": "0.8.1",
      "SHA1": "v+U1uTcAGJ2N1/EXGAJ7BWz5/SU="
    },
    {
      "Version": "0.9.3",
      "SHA1": "qvQ13U6yeeAxqKNsN5U7st1t0IM="
    }
  ],
  "ArchiveType": "jar"
}