{
  "GroupID": "systems.manifold",
  "ArtifactID": "manifold-tuple-rt",
  "Versions": [
    {
      "Version": "2022.1.15",
      "SHA1": "AlGJZiXY7+bWe+tYonb5gmZlYJY="
    },
    {
      "Version": "2022.1.16",
      "SHA1": "uG+Zz8IPdq+emK2+dwvuL/LpFYs="
    },
    {
      "Version": "2022.1.17",
      "SHA1": "IReextrIZphYNXS39qQQD0TZwEQ="
    },
    {
      "Version": "2022.1.18",
      "SHA1": "mx+lnT1ClXhpYXwq8JRm90i6yfY="
    },
    {
      "Version": "2022.1.19",
      "SHA1": "ZpdX/V+4vJm+4dyPwlnkFUM/awU="
    },
    {
      "Version": "2022.1.20",
      "SHA1": "XY4qQjefuO/UhUyf+NbuCuwAXT8="
    },
    {
      "Version": "2022.1.21",
      "SHA1": "wm0syqfBK2Kl/4GRuxQmTw/kx1Q="
    },
    {
      "Version": "2022.1.22",
      "SHA1": "z2hRQa/je4zEKduZeiIwKVE44po="
    },
    {
      "Version": "2022.1.23",
      "SHA1": "ExPkvrXbNfoysX4WTRYKi8CpW50="
    },
    {
      "Version": "2022.1.24",
      "SHA1": "OPIcUnTpAP4NzHgemkjeE6Afuhw="
    },
    {
      "Version": "2022.1.25",
      "SHA1": "7KwXci9AOLTtCDBmCIsZ0KDepq0="
    },
    {
      "Version": "2022.1.26",
      "SHA1": "pkEsU08pb53r+gzRewDmftOtiQI="
    },
    {
      "Version": "2022.1.27",
      "SHA1": "R8i1ojlPBfZ1rG88iq7Uv3DNZ3A="
    },
    {
      "Version": "2022.1.28",
      "SHA1": "NBCSRxOqz3HwZNUt5J1SHDIecno="
    },
    {
      "Version": "2022.1.29",
      "SHA1": "LYvYLoxJr9r94aUk0++aQ6MNeo0="
    },
    {
      "Version": "2022.1.30",
      "SHA1": "wmOaNjKkXBFRdV8IFM99qsEZbrE="
    },
    {
      "Version": "2022.1.31",
      "SHA1": "5enGC/XA08OAwPrPacQmSPuCUAQ="
    },
    {
      "Version": "2022.1.32",
      "SHA1": "ba8h8mnvarajoKUMsyaMD6877m0="
    },
    {
      "Version": "2022.1.33",
      "SHA1": "UtvLZeinmS+U/jKal7TASvuQYBo="
    },
    {
      "Version": "2022.1.34",
      "SHA1": "ZmmjcinN5Tz5u9rI9VOhHSIrCZQ="
    },
    {
      "Version": "2022.1.35",
      "SHA1": "lVM4Phx7kZReiqiY7Lc+957w1nA="
    },
    {
      "Version": "2022.1.36",
      "SHA1": "V7Xm7n5g9ruqH1J+YSBtq8yLh5w="
    },
    {
      "Version": "2022.1.37",
      "SHA1": "QMoPJgKceadzwKGwVx2wi2HgsZ8="
    },
    {
      "Version": "2022.1.38",
      "SHA1": "0OfZxlX5DIYjJ7ENIhcqP5B5YEs="
    },
    {
      "Version": "2023.1.0",
      "SHA1": "e3h0TV4KkUuTdKbw/nF+0bzkZqU="
    },
    {
      "Version": "2023.1.1",
      "SHA1": "pRJVcYRGaQqyHeXKld4P4O++hyc="
    },
    {
      "Version": "2023.1.2",
      "SHA1": "CcUXIjcSxd1Yj16BnblY9o27p10="
    },
    {
      "Version": "2023.1.3",
      "SHA1": "lHUqXY1o+hgh5+KErkGYJoRH18Q="
    },
    {
      "Version": "2023.1.4",
      "SHA1": "crU//vmMC5d4ICbnROxVbLrxCYU="
    },
    {
      "Version": "2023.1.5",
      "SHA1": "1pmL1STQm9zZ0SDzG5RTZrhpVPs="
    },
    {
      "Version": "2023.1.6",
      "SHA1": "aDBm9/yM4bqNAR+FchsS9DSAg3c="
    },
    {
      "Version": "2023.1.7",
      "SHA1": "BDPyVijlocCcLMkuV5XZQtJ27zQ="
    },
    {
      "Version": "2023.1.8",
      "SHA1": "9l9MXzyGNrwLkuP8gBY86jVFmeU="
    },
    {
      "Version": "2023.1.9",
      "SHA1": "E40DwFa/HFIGz7faHIkpmTL6MxQ="
    },
    {
      "Version": "2023.1.10",
      "SHA1": "qHbFSXnQdL/aVshDiCXuKn6D7iM="
    },
    {
      "Version": "2023.1.11",
      "SHA1": "SgGFWW6R1BXD/Jn9k8CLfiq7ClQ="
    },
    {
      "Version": "2023.1.12",
      "SHA1": "/zWkVT6kcTcbZ3bFACHxSpn4faI="
    },
    {
      "Version": "2023.1.13",
      "SHA1": "mxL3JGXSJjGQWQe8vsuyr4YpiRo="
    },
    {
      "Version": "2023.1.14",
      "SHA1": "ZNtf5hIhlGk8KnG5AMIXn75iUGo="
    },
    {
      "Version": "2023.1.15",
      "SHA1": "6RqSClamdsng3nbM9Z3jlmGD/UY="
    },
    {
      "Version": "2023.1.16",
      "SHA1": "pfvGOpIQLnBPyelPak/mv4V61tU="
    },
    {
      "Version": "2023.1.17",
      "SHA1": "vgseKbaswWGecSQZjhOFYJGZNkg="
    },
    {
      "Version": "2023.1.18",
      "SHA1": "8Svyw6FxZtfu7N2KuEmB6uPvBd0="
    },
    {
      "Version": "2023.1.19",
      "SHA1": "b9K+vL4Xol9ZQn6ZDnL61prmtFg="
    },
    {
      "Version": "2023.1.20",
      "SHA1": "PBlJMGMJ8It29JBR5dA18fgBnB4="
    },
    {
      "Version": "2023.1.21",
      "SHA1": "eKrXEonRqgr3pz1vVJsn/EPfxN8="
    },
    {
      "Version": "2023.1.22",
      "SHA1": "9uEKpnR+3vEpTSYh9pZgQpa+cgQ="
    },
    {
      "Version": "2023.1.24",
      "SHA1": "GH9jeGBpCYvNZ6yLt4eXo9iO9Zo="
    }
  ],
  "ArchiveType": "jar"
}